{"Command":"\"./kiro-go\"","CreatedAt":"2026-05-19 10:14:36 +0800 CST","ExitCode":0,"Health":"","ID":"153c66ba93dd","Image":"kiro-go-kiro-go","Labels":"com.docker.compose.config-hash=7a6363fd34c1797747106031c17fe2314d68a7c39facaaeb6f175ed02323bc0f,com.docker.compose.container-number=1,com.docker.compose.image=sha256:4b9b4d769681076b840a91e5f00ce13411170d2dd57845e233857a8d23d31cc0,com.docker.compose.project.config_files=/www/Kiro-Go/docker-compose.yml,com.docker.compose.project.working_dir=/www/Kiro-Go,com.docker.compose.replace=kiro-go-1,com.docker.compose.service=kiro-go,com.docker.compose.version=5.1.1,com.docker.compose.depends_on=,com.docker.compose.oneoff=False,com.docker.compose.project=kiro-go","LocalVolumes":"0","Mounts":"/www/Kiro-Go/d…","Name":"kiro-go-kiro-go-1","Names":"kiro-go-kiro-go-1","Networks":"kiro-go_default","Ports":"0.0.0.0:8080-\u003e8080/tcp, [::]:8080-\u003e8080/tcp","Project":"kiro-go","Publishers":[{"URL":"0.0.0.0","TargetPort":8080,"PublishedPort":8080,"Protocol":"tcp"},{"URL":"::","TargetPort":8080,"PublishedPort":8080,"Protocol":"tcp"}],"RunningFor":"15 seconds ago","Service":"kiro-go","Size":"0B","State":"running","Status":"Up 14 seconds"}
